Metadata-Version: 1.1
Name: cleanupd
Version: 0.9.0.2
Summary: A package providing additional object cleanup functionality.
Home-page: https://github.com/d-e-s-o/cleanup
Author: Daniel Mueller
Author-email: deso@posteo.net
License: GPLv3
Keywords: cleanup defer development
Platform: UNKNOWN
Classifier: Development Status :: 5 - Production/Stable
Classifier: Intended Audience :: Developers
Classifier: License :: OSI Approved :: GNU General Public License v3 (GPLv3)
Classifier: Operating System :: OS Independent
Classifier: Programming Language :: Python
Classifier: Programming Language :: Python :: 3
Classifier: Topic :: Software Development :: Libraries :: Python Modules
